LICENSE
MANIFEST.in
README.md
requirements.txt
setup.py
PyChunkedGraph.egg-info/PKG-INFO
PyChunkedGraph.egg-info/SOURCES.txt
PyChunkedGraph.egg-info/dependency_links.txt
PyChunkedGraph.egg-info/requires.txt
PyChunkedGraph.egg-info/top_level.txt
pychunkedgraph/__init__.py
pychunkedgraph/admin/__init__.py
pychunkedgraph/admin/bigtable_admin.py
pychunkedgraph/admin/table_prep.py
pychunkedgraph/app/__init__.py
pychunkedgraph/app/app_test.py
pychunkedgraph/app/app_utils.py
pychunkedgraph/app/cg_app_blueprint.py
pychunkedgraph/app/config.py
pychunkedgraph/app/meshing_app_blueprint.py
pychunkedgraph/backend/__init__.py
pychunkedgraph/backend/chunkedgraph.py
pychunkedgraph/backend/chunkedgraph_comp.py
pychunkedgraph/backend/chunkedgraph_exceptions.py
pychunkedgraph/backend/chunkedgraph_utils.py
pychunkedgraph/backend/cutting.py
pychunkedgraph/backend/cutting_test.py
pychunkedgraph/backend/flatgraph_utils.py
pychunkedgraph/backend/utils/__init__.py
pychunkedgraph/backend/utils/basetypes.py
pychunkedgraph/backend/utils/column_keys.py
pychunkedgraph/backend/utils/row_keys.py
pychunkedgraph/backend/utils/serializers.py
pychunkedgraph/benchmarking/__init__.py
pychunkedgraph/benchmarking/datasets.py
pychunkedgraph/benchmarking/graph_measurements.py
pychunkedgraph/benchmarking/simulator.py
pychunkedgraph/benchmarking/timings.py
pychunkedgraph/creator/__init__.py
pychunkedgraph/creator/chunkcreator.py
pychunkedgraph/creator/creator_utils.py
pychunkedgraph/creator/data_test.py
pychunkedgraph/creator/graph_tests.py
pychunkedgraph/exporting/__init__.py
pychunkedgraph/exporting/export.py
pychunkedgraph/ingest/__init__.py
pychunkedgraph/ingest/ingestion_utils.py
pychunkedgraph/ingest/ingestionmanager.py
pychunkedgraph/ingest/ran_ingestion.py
pychunkedgraph/logging/__init__.py
pychunkedgraph/logging/flask_log_db.py
pychunkedgraph/logging/jsonformatter.py
pychunkedgraph/logging/performance.py
pychunkedgraph/meshing/__init__.py
pychunkedgraph/meshing/mesh_io.py
pychunkedgraph/meshing/meshengine.py
pychunkedgraph/meshing/meshgen.py
pychunkedgraph/meshing/meshgen_utils.py
pychunkedgraph/meshing/meshlabserver.py
pychunkedgraph/rechunking/__init__.py
