Metadata-Version: 2.1
Name: PyChunkedGraph
Version: 0.1.113
Summary: Proofreading backend for Neuroglancer
Home-page: https://github.com/seung-lab/PyChunkedGraph
Author: Sven Dorkenwald
Author-email: svenmd@princeton.edu
License: UNKNOWN
Platform: UNKNOWN
Classifier: Programming Language :: Python :: 3
Classifier: License :: OSI Approved :: MIT License
Classifier: Operating System :: POSIX :: Linux
